Workbook

Sheet Dashboard
A1: QSR Franchise Portfolio — Financial Forecast Model | FY 2025–2029
A2: Navigation: Dashboard (this tab) | 5-Year Forecast | Location Scoring | New Location Analyzer | Scenario Planner
A4: PORTFOLIO SNAPSHOT — CURRENT YEAR (2025)
A5: Metric | B5: Little Caesars | C5: Arby's | D5: Wingstop | E5: Portfolio Total | G5: Trend | H5: vs. Prior Yr
A6: Locations | B6: 4 | C6: 3 | D6: 3 | E6: 10 | G6: — | H6: —
A7: Avg Annual Revenue / Unit | B7: $720K | C7: $738K | D7: $968K | E7: $808K | G7: ↑ | H7: +4.2%
A8: Total Portfolio Revenue | B8: $2.88M | C8: $2.21M | D8: $2.90M | E8: $8.00M | G8: ↑ | H8: +4.2%
A9: Blended Gross Margin | B9: 40.5% | C9: 38.0% | D9: 39.2% | E9: 39.4% | G9: → | H9: +0.3pp
A10: Portfolio EBITDA | B10: $820K | C10: $490K | D10: $703K | E10: $2.01M | G10: ↑ | H10: +5.1%
A11: Blended EBITDA Margin | B11: 28.5% | C11: 22.2% | D11: 24.2% | E11: 25.1% | G11: ↑ | H11: +0.7pp
A12: Avg Payback Period | B12: 3.2 yr | C12: 4.1 yr | D12: 3.6 yr | E12: 3.6 yr | G12: → | H12: —
A14: 5-YEAR REVENUE FORECAST — PORTFOLIO TOTAL ($)
A15: Brand / Location | B15: 2025 | C15: 2026 | D15: 2027 | E15: 2028 | F15: 2029 | G15: CAGR | H15: Total (5yr)
A16: Little Caesars (4 units) | B16: 2880000 | C16: 3024000 | D16: 3175200 | E16: 3333960 | F16: 3500658 | G16: 6.5% | H16: 15913818
A17: Arby's (3 units) | B17: 2214000 | C17: 2280420 | D17: 2348833 | E17: 2419298 | F17: 2491877 | G17: 3.0% | H17: 11754428
A18: Wingstop (3 units) | B18: 2904000 | C18: 3136320 | D18: 3387226 | E18: 3658204 | F18: 3950780 | G18: 8.0% | H18: 17036530
A19: Portfolio Total | B19: 7998000 | C19: 8440740 | D19: 8911259 | E19: 9411462 | F19: 9943315 | G19: 5.7% | H19: 44704776
A21: GLOBAL FORECAST ASSUMPTIONS (edit yellow cells — all tabs update)
A22: Little Caesars — Annual Revenue Growth | B22: 0.05 | C22: ← Summer/family + holiday seasonality driver
A23: Arby's — Annual Revenue Growth | B23: 0.03 | C23: ← Drive-thru consistency; modest same-store growth
A24: Wingstop — Annual Revenue Growth | B24: 0.08 | C24: ← NFL expansion, delivery platform growth
A25: Inflation Assumption (Cost Escalator) | B25: 0.03 | C25: ← Applied to rent, utilities, and fixed labor annually
A26: New Location Build-Out Cost | B26: 450000 | C26: ← Avg per unit; used in payback/ROI calculations
A27: Target EBITDA Margin — Threshold | B27: 0.2 | C27: ← Min acceptable margin for new location Go/No-Go
A28: Discount Rate (for NPV calc) | B28: 0.1 | C28: ← Used in New Location Analyzer tab
A30: HOW TO USE THIS MODEL
A31: 1 Dashboard | B31: Global assumptions + portfolio KPI snapshot. Edit yellow cells here first.
A32: 2 5-Year Forecast | B32: Full revenue, EBITDA, and margin projection for all 10 locations across 5 years.
A33: 3 Location Scoring | B33: Demographic + competitive scoring for each location. Drives revenue adjustments.
A34: 4 New Location Analyzer | B34: Enter a proposed site's details. Model outputs break-even, ROI, payback, and Go/No-Go.
A35: 5 Scenario Planner | B35: Toggle between Base, Upside, and Downside cases. See full P&L impact across the portfolio.

Sheet 5-Year Forecast
A1: 5-Year Financial Forecast — All Locations | Base Case
A2: Revenue grows by brand growth rate (Dashboard B22:B24). Costs escalate by inflation rate (Dashboard B25). All figures USD.
A4: ANNUAL REVENUE FORECAST ($)
A5: Location | B5: Brand | C5: 2025 | D5: 2026 | E5: 2027 | F5: 2028 | G5: 2029 | H5: CAGR | I5: 5-Yr Total
A6: Little Caesars Location 1 | B6: LI | C6: 720000 | D6: =C6*(1+Dashboard!$B$22) -> 756000 | E6: =D6*(1+Dashboard!$B$22) -> 793800 | F6: =E6*(1+Dashboard!$B$22) -> 833490 | G6: =F6*(1+Dashboard!$B$22) -> 875164.5 | H6: =IF(C6=0,0,(G6/C6)^(1/4)-1) -> 0.05 | I6: =SUM(C6:G6) -> 3978454.5
A7: Little Caesars Location 2 | B7: LI | C7: 756000 | D7: =C7*(1+Dashboard!$B$22) -> 793800 | E7: =D7*(1+Dashboard!$B$22) -> 833490 | F7: =E7*(1+Dashboard!$B$22) -> 875164.5 | G7: =F7*(1+Dashboard!$B$22) -> 918922.72 | H7: =IF(C7=0,0,(G7/C7)^(1/4)-1) -> 0.05 | I7: =SUM(C7:G7) -> 4177377.2
A8: Little Caesars Location 3 | B8: LI | C8: 696000 | D8: =C8*(1+Dashboard!$B$22) -> 730800 | E8: =D8*(1+Dashboard!$B$22) -> 767340 | F8: =E8*(1+Dashboard!$B$22) -> 805707 | G8: =F8*(1+Dashboard!$B$22) -> 845992.35 | H8: =IF(C8=0,0,(G8/C8)^(1/4)-1) -> 0.05 | I8: =SUM(C8:G8) -> 3845839.4
A9: Little Caesars Location 4 | B9: LI | C9: 744000 | D9: =C9*(1+Dashboard!$B$22) -> 781200 | E9: =D9*(1+Dashboard!$B$22) -> 820260 | F9: =E9*(1+Dashboard!$B$22) -> 861273 | G9: =F9*(1+Dashboard!$B$22) -> 904336.65 | H9: =IF(C9=0,0,(G9/C9)^(1/4)-1) -> 0.05 | I9: =SUM(C9:G9) -> 4111069.6
A10: Arby's Location 1 | B10: AR | C10: 900000 | D10: =C10*(1+Dashboard!$B$23) -> 927000 | E10: =D10*(1+Dashboard!$B$23) -> 954810 | F10: =E10*(1+Dashboard!$B$23) -> 983454.3 | G10: =F10*(1+Dashboard!$B$23) -> 1012957.9 | H10: =IF(C10=0,0,(G10/C10)^(1/4)-1) -> 0.03 | I10: =SUM(C10:G10) -> 4778222.2
A11: Arby's Location 2 | B11: AR | C11: 864000 | D11: =C11*(1+Dashboard!$B$23) -> 889920 | E11: =D11*(1+Dashboard!$B$23) -> 916617.6 | F11: =E11*(1+Dashboard!$B$23) -> 944116.13 | G11: =F11*(1+Dashboard!$B$23) -> 972439.61 | H11: =IF(C11=0,0,(G11/C11)^(1/4)-1) -> 0.03 | I11: =SUM(C11:G11) -> 4587093.3
A12: Arby's Location 3 | B12: AR | C12: 888000 | D12: =C12*(1+Dashboard!$B$23) -> 914640 | E12: =D12*(1+Dashboard!$B$23) -> 942079.2 | F12: =E12*(1+Dashboard!$B$23) -> 970341.58 | G12: =F12*(1+Dashboard!$B$23) -> 999451.82 | H12: =IF(C12=0,0,(G12/C12)^(1/4)-1) -> 0.03 | I12: =SUM(C12:G12) -> 4714512.6
A13: Wingstop Location 1 | B13: WI | C13: 984000 | D13: =C13*(1+Dashboard!$B$24) -> 1062720 | E13: =D13*(1+Dashboard!$B$24) -> 1147737.6 | F13: =E13*(1+Dashboard!$B$24) -> 1239556.6 | G13: =F13*(1+Dashboard!$B$24) -> 1338721.1 | H13: =IF(C13=0,0,(G13/C13)^(1/4)-1) -> 0.08 | I13: =SUM(C13:G13) -> 5772735.3
A14: Wingstop Location 2 | B14: WI | C14: 960000 | D14: =C14*(1+Dashboard!$B$24) -> 1036800 | E14: =D14*(1+Dashboard!$B$24) -> 1119744 | F14: =E14*(1+Dashboard!$B$24) -> 1209323.5 | G14: =F14*(1+Dashboard!$B$24) -> 1306069.4 | H14: =IF(C14=0,0,(G14/C14)^(1/4)-1) -> 0.08 | I14: =SUM(C14:G14) -> 5631936.9
A15: Wingstop Location 3 | B15: WI | C15: 984000 | D15: =C15*(1+Dashboard!$B$24) -> 1062720 | E15: =D15*(1+Dashboard!$B$24) -> 1147737.6 | F15: =E15*(1+Dashboard!$B$24) -> 1239556.6 | G15: =F15*(1+Dashboard!$B$24) -> 1338721.1 | H15: =IF(C15=0,0,(G15/C15)^(1/4)-1) -> 0.08 | I15: =SUM(C15:G15) -> 5772735.3
A16: Little Caesars Subtotal | C16: =C6+C7+C8+C9 -> 2916000 | D16: =D6+D7+D8+D9 -> 3061800 | E16: =E6+E7+E8+E9 -> 3214890 | F16: =F6+F7+F8+F9 -> 3375634.5 | G16: =G6+G7+G8+G9 -> 3544416.2 | H16: =IF(C16=0,0,(G16/C16)^(1/4)-1) -> 0.05 | I16: =SUM(C16:G16) -> 16112741
A17: Arby's Subtotal | C17: =C10+C11+C12 -> 2652000 | D17: =D10+D11+D12 -> 2731560 | E17: =E10+E11+E12 -> 2813506.8 | F17: =F10+F11+F12 -> 2897912 | G17: =G10+G11+G12 -> 2984849.4 | H17: =IF(C17=0,0,(G17/C17)^(1/4)-1) -> 0.03 | I17: =SUM(C17:G17) -> 14079828
A18: Wingstop Subtotal | C18: =C13+C14+C15 -> 2928000 | D18: =D13+D14+D15 -> 3162240 | E18: =E13+E14+E15 -> 3415219.2 | F18: =F13+F14+F15 -> 3688436.7 | G18: =G13+G14+G15 -> 3983511.7 | H18: =IF(C18=0,0,(G18/C18)^(1/4)-1) -> 0.08 | I18: =SUM(C18:G18) -> 17177408
A19: PORTFOLIO TOTAL | C19: =C16+C17+C18 -> 8496000 | D19: =D16+D17+D18 -> 8955600 | E19: =E16+E17+E18 -> 9443616 | F19: =F16+F17+F18 -> 9961983.2 | G19: =G16+G17+G18 -> 10512777 | H19: =IF(C19=0,0,(G19/C19)^(1/4)-1) -> 0.054692214 | I19: =SUM(C19:G19) -> 47369977
A21: EBITDA FORECAST ($) — Base Case Margins Applied
A22: Location | B22: Brand | C22: 2025 | D22: 2026 | E22: 2027 | F22: 2028 | G22: 2029 | H22: Avg Margin | I22: 5-Yr EBITDA
A23: Little Caesars Location 1 | B23: LI | C23: =C6*0.285 -> 205200 | D23: =D6*0.29 -> 219240 | E23: =E6*0.295 -> 234171 | F23: =F6*0.298 -> 248380.02 | G23: =G6*0.3 -> 262549.35 | H23: =AVERAGE(C23:G23)/AVERAGE(C6:G6) -> 0.29396852 | I23: =SUM(C23:G23) -> 1169540.4
A24: Little Caesars Location 2 | B24: LI | C24: =C7*0.285 -> 215460 | D24: =D7*0.29 -> 230202 | E24: =E7*0.295 -> 245879.55 | F24: =F7*0.298 -> 260799.02 | G24: =G7*0.3 -> 275676.82 | H24: =AVERAGE(C24:G24)/AVERAGE(C7:G7) -> 0.29396852 | I24: =SUM(C24:G24) -> 1228017.4
A25: Little Caesars Location 3 | B25: LI | C25: =C8*0.285 -> 198360 | D25: =D8*0.29 -> 211932 | E25: =E8*0.295 -> 226365.3 | F25: =F8*0.298 -> 240100.69 | G25: =G8*0.3 -> 253797.7 | H25: =AVERAGE(C25:G25)/AVERAGE(C8:G8) -> 0.29396852 | I25: =SUM(C25:G25) -> 1130555.7
A26: Little Caesars Location 4 | B26: LI | C26: =C9*0.285 -> 212040 | D26: =D9*0.29 -> 226548 | E26: =E9*0.295 -> 241976.7 | F26: =F9*0.298 -> 256659.35 | G26: =G9*0.3 -> 271300.99 | H26: =AVERAGE(C26:G26)/AVERAGE(C9:G9) -> 0.29396852 | I26: =SUM(C26:G26) -> 1208525
A27: Arby's Location 1 | B27: AR | C27: =C10*0.222 -> 199800 | D27: =D10*0.225 -> 208575 | E27: =E10*0.228 -> 217696.68 | F27: =F10*0.23 -> 226194.49 | G27: =G10*0.232 -> 235006.24 | H27: =AVERAGE(C27:G27)/AVERAGE(C10:G10) -> 0.22754748 | I27: =SUM(C27:G27) -> 1087272.4
A28: Arby's Location 2 | B28: AR | C28: =C11*0.222 -> 191808 | D28: =D11*0.225 -> 200232 | E28: =E11*0.228 -> 208988.81 | F28: =F11*0.23 -> 217146.71 | G28: =G11*0.232 -> 225605.99 | H28: =AVERAGE(C28:G28)/AVERAGE(C11:G11) -> 0.22754748 | I28: =SUM(C28:G28) -> 1043781.5
A29: Arby's Location 3 | B29: AR | C29: =C12*0.222 -> 197136 | D29: =D12*0.225 -> 205794 | E29: =E12*0.228 -> 214794.06 | F29: =F12*0.23 -> 223178.56 | G29: =G12*0.232 -> 231872.82 | H29: =AVERAGE(C29:G29)/AVERAGE(C12:G12) -> 0.22754748 | I29: =SUM(C29:G29) -> 1072775.4
A30: Wingstop Location 1 | B30: WI | C30: =C13*0.242 -> 238128 | D30: =D13*0.248 -> 263554.56 | E30: =E13*0.252 -> 289229.88 | F30: =F13*0.256 -> 317326.49 | G30: =G13*0.26 -> 348067.5 | H30: =AVERAGE(C30:G30)/AVERAGE(C13:G13) -> 0.2522732 | I30: =SUM(C30:G30) -> 1456306.4
A31: Wingstop Location 2 | B31: WI | C31: =C14*0.242 -> 232320 | D31: =D14*0.248 -> 257126.4 | E31: =E14*0.252 -> 282175.49 | F31: =F14*0.256 -> 309586.82 | G31: =G14*0.26 -> 339578.04 | H31: =AVERAGE(C31:G31)/AVERAGE(C14:G14) -> 0.2522732 | I31: =SUM(C31:G31) -> 1420786.8
A32: Wingstop Location 3 | B32: WI | C32: =C15*0.242 -> 238128 | D32: =D15*0.248 -> 263554.56 | E32: =E15*0.252 -> 289229.88 | F32: =F15*0.256 -> 317326.49 | G32: =G15*0.26 -> 348067.5 | H32: =AVERAGE(C32:G32)/AVERAGE(C15:G15) -> 0.2522732 | I32: =SUM(C32:G32) -> 1456306.4
A33: Little Caesars EBITDA Subtotal | C33: =C23+C24+C25+C26 -> 831060 | D33: =D23+D24+D25+D26 -> 887922 | E33: =E23+E24+E25+E26 -> 948392.55 | F33: =F23+F24+F25+F26 -> 1005939.1 | G33: =G23+G24+G25+G26 -> 1063324.9 | I33: =SUM(I23:I26) -> 4736638.5
A34: Arby's EBITDA Subtotal | C34: =C27+C28+C29 -> 588744 | D34: =D27+D28+D29 -> 614601 | E34: =E27+E28+E29 -> 641479.55 | F34: =F27+F28+F29 -> 666519.76 | G34: =G27+G28+G29 -> 692485.05 | I34: =SUM(I27:I29) -> 3203829.4
A35: Wingstop EBITDA Subtotal | C35: =C30+C31+C32 -> 708576 | D35: =D30+D31+D32 -> 784235.52 | E35: =E30+E31+E32 -> 860635.24 | F35: =F30+F31+F32 -> 944239.8 | G35: =G30+G31+G32 -> 1035713 | I35: =SUM(I30:I32) -> 4333399.6
A36: PORTFOLIO EBITDA TOTAL | C36: =C33+C34+C35 -> 2128380 | D36: =D33+D34+D35 -> 2286758.5 | E36: =E33+E34+E35 -> 2450507.3 | F36: =F33+F34+F35 -> 2616698.6 | G36: =G33+G34+G35 -> 2791523 | H36: =I36/I19 -> 0.25910647 | I36: =SUM(I33:I35) -> 12273867

Sheet Location Scoring
A1: Location Scoring Matrix — Demographic & Competitive Analysis
A2: Each factor scored 1–10. Weighted score drives Revenue Adjustment % applied in 5-Year Forecast. Edit yellow cells.
A4: SCORING WEIGHTS (must sum to 100%)
A5: Factor | B5: Weight | C5: Notes
A6: Population Density | B6: 0.25 | C6: Higher density = larger addressable market
A7: Household Income (Avg) | B7: 0.2 | C7: Purchasing power drives ticket size & frequency
A8: Foot Traffic Score | B8: 0.25 | C8: Direct driver of walk-in and impulse visits
A9: Competitor Proximity | B9: 0.15 | C9: Fewer nearby competitors = less revenue dilution
A10: Visibility / Signage | B10: 0.1 | C10: Road visibility and parking ease
A11: Brand Fit (Demo Match) | B11: 0.05 | C11: Brand's target customer vs. local demographic
A12: Weight Total (must = 100%) | B12: =SUM(B6:B11) -> 1 | C12: ✓ Verify this equals 100% before using scores
A14: LOCATION SCORES (1=Low, 10=High) — Edit yellow cells
A15: Location | B15: Brand | C15: Pop Density | D15: HH Income | E15: Foot Traffic | F15: Competition | G15: Visibility | H15: Brand Fit | I15: Wtd Score
A16: Little Caesars Location 1 | B16: LI | C16: 7 | D16: 6 | E16: 8 | F16: 7 | G16: 7 | H16: 8 | I16: =C16*$B$6+D16*$B$7+E16*$B$8+F16*$B$9+G16*$B$10+H16*$B$11 -> 7.1
A17: Little Caesars Location 2 | B17: LI | C17: 8 | D17: 5 | E17: 7 | F17: 6 | G17: 8 | H17: 8 | I17: =C17*$B$6+D17*$B$7+E17*$B$8+F17*$B$9+G17*$B$10+H17*$B$11 -> 6.85
A18: Little Caesars Location 3 | B18: LI | C18: 6 | D18: 6 | E18: 7 | F18: 8 | G18: 6 | H18: 8 | I18: =C18*$B$6+D18*$B$7+E18*$B$8+F18*$B$9+G18*$B$10+H18*$B$11 -> 6.65
A19: Little Caesars Location 4 | B19: LI | C19: 7 | D19: 7 | E19: 8 | F19: 7 | G19: 7 | H19: 8 | I19: =C19*$B$6+D19*$B$7+E19*$B$8+F19*$B$9+G19*$B$10+H19*$B$11 -> 7.3
A20: Arby's Location 1 | B20: AR | C20: 6 | D20: 7 | E20: 9 | F20: 6 | G20: 9 | H20: 7 | I20: =C20*$B$6+D20*$B$7+E20*$B$8+F20*$B$9+G20*$B$10+H20*$B$11 -> 7.3
A21: Arby's Location 2 | B21: AR | C21: 7 | D21: 6 | E21: 8 | F21: 7 | G21: 8 | H21: 7 | I21: =C21*$B$6+D21*$B$7+E21*$B$8+F21*$B$9+G21*$B$10+H21*$B$11 -> 7.15
A22: Arby's Location 3 | B22: AR | C22: 5 | D22: 7 | E22: 8 | F22: 8 | G22: 7 | H22: 7 | I22: =C22*$B$6+D22*$B$7+E22*$B$8+F22*$B$9+G22*$B$10+H22*$B$11 -> 6.9
A23: Wingstop Location 1 | B23: WI | C23: 8 | D23: 6 | E23: 8 | F23: 6 | G23: 7 | H23: 9 | I23: =C23*$B$6+D23*$B$7+E23*$B$8+F23*$B$9+G23*$B$10+H23*$B$11 -> 7.25
A24: Wingstop Location 2 | B24: WI | C24: 7 | D24: 7 | E24: 7 | F24: 7 | G24: 7 | H24: 9 | I24: =C24*$B$6+D24*$B$7+E24*$B$8+F24*$B$9+G24*$B$10+H24*$B$11 -> 7.1
A25: Wingstop Location 3 | B25: WI | C25: 8 | D25: 6 | E25: 9 | F25: 5 | G25: 8 | H25: 9 | I25: =C25*$B$6+D25*$B$7+E25*$B$8+F25*$B$9+G25*$B$10+H25*$B$11 -> 7.45
A27: SCORE-TO-REVENUE ADJUSTMENT KEY
A28: Weighted Score Range | B28: Revenue Adjustment | C28: Interpretation
A29: 8.5 – 10.0 | B29: +10% to +15% | C29: Exceptional site — premium revenue potential
A30: 7.0 – 8.4 | B30: +3% to +10% | C30: Strong site — above-average revenue expected
A31: 5.5 – 6.9 | B31: Base (0%) | C31: Average site — use base revenue assumptions
A32: 4.0 – 5.4 | B32: -5% to -10% | C32: Below-average site — discount revenue expectations
A33: Below 4.0 | B33: -15% or more | C33: Weak site — consider alternative location

Sheet New Location Analyzer
A1: New Location Viability Analyzer — Site Evaluation & ROI
A2: Enter proposed site details in yellow cells. Model outputs Go/No-Go, break-even, payback period, and 5-year NPV.
A4: PROPOSED SITE INPUTS
A5: Brand | B5: Wingstop | C5: ← Select: Little Caesars, Arby's, or Wingstop
A6: Location Description | B6: Proposed Site A | C6: ← Enter city/market description
A7: Projected Annual Revenue (Yr 1) | B7: 820000 | C7: ← Based on comparable units + location score
A8: Buildout / Opening Cost ($) | B8: 450000 | C8: ← Source: Dashboard assumption (edit to override)
A9: Monthly Rent ($) | B9: 7500 | C9: ← Negotiated lease rate
A10: Food Cost (% of Revenue) | B10: 0.33 | C10: ← Use brand benchmark as starting point
A11: Labor Cost (% of Revenue) | B11: 0.21 | C11: ← Variable + fixed blended estimate
A12: Other Operating Costs (% of Rev) | B12: 0.15 | C12: ← Utilities, marketing, misc combined
A13: Annual Revenue Growth Rate (%) | B13: 0.08 | C13: ← Source: Dashboard brand growth assumption
A14: Location Score (from Scoring tab) | B14: 7.8 | C14: ← Pull from Location Scoring tab weighted score
A15: Discount Rate | B15: 0.1 | C15: ← Source: Dashboard assumption
A17: VIABILITY OUTPUTS — AUTO-CALCULATED
A18: Metric | B18: Year 1 | C18: Year 2 | D18: Year 3 | E18: Year 4 | F18: Year 5
A19: Projected Revenue | B19: =B7*(1+B13)^0 -> 820000 | C19: =B7*(1+B13)^1 -> 885600 | D19: =B7*(1+B13)^2 -> 956448 | E19: =B7*(1+B13)^3 -> 1032963.8 | F19: =B7*(1+B13)^4 -> 1115600.9
A20: COGS | B20: =C19*(B10+0.02) -> 309960 | C20: =D19*(B10+0.02) -> 334756.8 | D20: =E19*(B10+0.02) -> 361537.34 | E20: =F19*(B10+0.02) -> 390460.33 | F20: =G19*(B10+0.02) -> 0
A21: Gross Profit | B21: =C19-C20 -> 550843.2 | C21: =D19-D20 -> 594910.66 | D21: =E19-E20 -> 642503.51 | E21: =F19-F20 -> 1115600.9 | F21: =G19-G20 -> 0
A22: Labor | B22: =C19*B11 -> 185976 | C22: =D19*B11 -> 200854.08 | D22: =E19*B11 -> 216922.41 | E22: =F19*B11 -> 234276.2 | F22: =G19*B11 -> 0
A23: Rent (Annual) | B23: =B9*12 -> 90000 | C23: =B9*12*(1+Dashboard!$B$25)^1 -> 92700 | D23: =B9*12*(1+Dashboard!$B$25)^2 -> 95481 | E23: =B9*12*(1+Dashboard!$B$25)^3 -> 98345.43 | F23: =B9*12*(1+Dashboard!$B$25)^4 -> 101295.79
A24: Other Operating | B24: =C19*B12 -> 132840 | C24: =D19*B12 -> 143467.2 | D24: =E19*B12 -> 154944.58 | E24: =F19*B12 -> 167340.14 | F24: =G19*B12 -> 0
A25: Total OpEx | B25: =C22+C23+C24 -> 437021.28 | C25: =D22+D23+D24 -> 467347.98 | D25: =E22+E23+E24 -> 499961.77 | E25: =F22+F23+F24 -> 101295.79 | F25: =G22+G23+G24 -> 0
A26: EBITDA | B26: =C21-C25 -> 127562.67 | C26: =D21-D25 -> 142541.74 | D26: =E21-E25 -> 1014305.2 | E26: =F21-F25 -> 0 | F26: =G21-G25 -> 0
A27: EBITDA Margin % | B27: =IF(C19=0,0,C26/C19) -> 0.16095499 | C27: =IF(D19=0,0,D26/D19) -> 1.0604917 | D27: =IF(E19=0,0,E26/E19) -> 0 | E27: =IF(F19=0,0,F26/F19) -> 0 | F27: =IF(G19=0,0,G26/G19) -> 0
A28: Cumulative Cash Flow | B28: =-B8+B26 -> -322437.33 | C28: =B28+C26 -> -179895.59 | D28: =C28+D26 -> 834409.57 | E28: =D28+E26 -> 834409.57 | F28: =E28+F26 -> 834409.57
A30: SUMMARY DECISION METRICS
A31: Year 1 EBITDA | B31: =C26 -> 142541.74 | C31: EBITDA generated in the first 12 months of operation
A32: Year 1 EBITDA Margin | B32: =C27 -> 1.0604917 | C32: First-year profitability as a % of revenue
A33: Break-Even Month (approx) | B33: =IF(C26>0,12*B8/C26,99) -> 37.883641 | C33: Approximate month when cumulative EBITDA covers buildout cost
A34: Payback Period (years) | B34: =IF(C26>0,B8/C26,99) -> 3.1569701 | C34: Years to fully recover the buildout investment from EBITDA
A35: 5-Year Cumulative EBITDA | B35: =SUM(C26:G26) -> 1156846.9 | C35: Total EBITDA generated across the 5-year forecast window
A36: 5-Yr NPV of EBITDA | B36: =NPV(B15,C26,D26,E26,F26,G26)-B8 -> 517852.12 | C36: Present value of 5-year EBITDA discounted at your hurdle rate, net of buildout
A37: Investment Multiple (MOIC) | B37: =IF(B8=0,0,(SUM(C26:G26)+B8)/B8) -> 3.5707709 | C37: Total EBITDA return per $1 of buildout invested
A38: GO / NO-GO | B38: =IF(C27>=Dashboard!$B$26,IF(B8/C26<=5,"GO","REVIEW"),"NO-GO") -> NO-GO | C38: GO if Year 1 margin ≥ threshold and payback ≤ 5 years. REVIEW if borderline. NO-GO if below threshold.

Sheet Scenario Planner
A1: Scenario Planner — Base / Upside / Downside Analysis
A2: Edit the yellow assumption cells for each scenario. See full P&L and EBITDA impact across all 10 locations.
A4: SCENARIO ASSUMPTIONS — Edit Yellow Cells
A5: Assumption | B5: Base Case | C5: Upside Case | D5: Downside Case | E5: Notes
A6: LC Revenue Growth (Annual) | B6: 0.05 | C6: 0.08 | D6: 0.02 | E6: Little Caesars YoY same-store growth
A7: Arby's Revenue Growth | B7: 0.03 | C7: 0.05 | D7: 0.01 | E7: Arby's YoY same-store growth
A8: Wingstop Revenue Growth | B8: 0.08 | C8: 0.12 | D8: 0.03 | E8: Wingstop YoY growth incl. delivery expansion
A9: Food Cost % (blended) | B9: 0.3 | C9: 0.285 | D9: 0.32 | E9: Portfolio average; Wingstop most volatile
A10: Labor Cost % (blended) | B10: 0.22 | C10: 0.21 | D10: 0.24 | E10: Reflects hiring environment + min wage changes
A11: Rent Escalation (annual) | B11: 0.03 | C11: 0.02 | D11: 0.045 | E11: Lease renewal exposure
A12: Utility Cost Inflation | B12: 0.03 | C12: 0.02 | D12: 0.06 | E12: Energy price sensitivity
A13: Marketing % of Revenue | B13: 0.04 | C13: 0.035 | D13: 0.045 | E13: Brand co-op + local spend
A14: New Location Opens (yr) | B14: 1 | C14: 2 | D14: 0 | E14: Planned expansion pace
A16: PORTFOLIO REVENUE FORECAST BY SCENARIO ($)
A17: Year | B17: Base Revenue | C17: Upside Revenue | D17: Downside Revenue | E17: Base EBITDA | F17: Downside EBITDA
A18: 2025 | B18: =8000000 -> 8000000 | C18: =8000000 -> 8000000 | D18: =8000000 -> 8000000 | E18: =B18*(1-$B$9-$B$10-0.12-0.02-$B$13) -> 2400000 | F18: =D18*(1-$D$9-$D$10-0.14-0.025-$D$13) -> 1840000
A19: 2026 | B19: =B18*(1+(0.36*$B$6+0.27675*$B$7+0.363*$B$8)) -> 8442740 | C19: =C18*(1+(0.36*$C$6+0.27675*$C$7+0.363*$C$8)) -> 8689580 | D19: =D18*(1+(0.36*$D$6+0.27675*$D$7+0.363*$D$8)) -> 8166860 | E19: =B19*(1-$B$9-$B$10-0.12-0.02-$B$13) -> 2532822 | F19: =D19*(1-$D$9-$D$10-0.14-0.025-$D$13) -> 1878377.8
A20: 2027 | B20: =B19*(1+(0.36*$B$6+0.27675*$B$7+0.363*$B$8)) -> 8909982.3 | C20: =C19*(1+(0.36*$C$6+0.27675*$C$7+0.363*$C$8)) -> 9438600.1 | D20: =D19*(1+(0.36*$D$6+0.27675*$D$7+0.363*$D$8)) -> 8337200.3 | E20: =B20*(1-$B$9-$B$10-0.12-0.02-$B$13) -> 2672994.7 | F20: =D20*(1-$D$9-$D$10-0.14-0.025-$D$13) -> 1917556.1
A21: 2028 | B21: =B20*(1+(0.36*$B$6+0.27675*$B$7+0.363*$B$8)) -> 9403083 | C21: =C20*(1+(0.36*$C$6+0.27675*$C$7+0.363*$C$8)) -> 10252184 | D21: =D20*(1+(0.36*$D$6+0.27675*$D$7+0.363*$D$8)) -> 8511093.4 | E21: =B21*(1-$B$9-$B$10-0.12-0.02-$B$13) -> 2820924.9 | F21: =D21*(1-$D$9-$D$10-0.14-0.025-$D$13) -> 1957551.5
A22: 2029 | B22: =B21*(1+(0.36*$B$6+0.27675*$B$7+0.363*$B$8)) -> 9923473.2 | C22: =C21*(1+(0.36*$C$6+0.27675*$C$7+0.363*$C$8)) -> 11135896 | D22: =D21*(1+(0.36*$D$6+0.27675*$D$7+0.363*$D$8)) -> 8688613.6 | E22: =B22*(1-$B$9-$B$10-0.12-0.02-$B$13) -> 2977041.9 | F22: =D22*(1-$D$9-$D$10-0.14-0.025-$D$13) -> 1998381.1
A24: SENSITIVITY ANALYSIS — EBITDA IMPACT OF KEY LEVERS
A25: Lever | B25: Change | C25: EBITDA Impact (Yr 1 Est.) | D25: Direction | E25: Severity | F25: Action
A26: Revenue -5% | B26: -5% all brands | C26: ($400K) | D26: ▼ | E26: HIGH | F26: Tighten marketing spend; review pricing
A27: Food Cost +2pp | B27: +2% blended | C27: ($160K) | D27: ▼ | E27: HIGH | F27: Renegotiate supplier contracts
A28: Labor Cost +1pp | B28: +1% blended | C28: ($80K) | D28: ▼ | E28: MED | F28: Optimize scheduling; reduce overtime
A29: Rent Escalation +10% | B29: +10% at renewal | C29: ($65K) | D29: ▼ | E29: MED | F29: Lock multi-year leases before renewals
A30: Wingstop Rev +8% | B30: NFL season upside | C30: +$235K | D30: ▲ | E30: HIGH | F30: Capitalize on NFL promotions in Sep-Jan
A31: New Unit Opens (×2) | B31: Add 2 locations | C31: +$450K | D31: ▲ | E31: HIGH | F31: Prioritize high-score sites from Scoring tab
A32: Delivery Mix +5pp | B32: Channel shift | C32: +$120K | D32: ▲ | E32: MED | F32: Wingstop/LC focus; 3P platform optimization
